context_llemur-0.2.2.dist-info/licenses/LICENSE
src/__init__.py
src/cli_styles.py
src/ctx_core.py
src/main.py
src/mcp_server.py
src/template/ctx.txt
src/template/goals.txt
src/template/rules.txt
context_llemur-0.2.2.dist-info/METADATA
context_llemur-0.2.2.dist-info/WHEEL
context_llemur-0.2.2.dist-info/entry_points.txt
context_llemur-0.2.2.dist-info/top_level.txt
context_llemur-0.2.2.dist-info/RECORD
