Metadata-Version: 2.4
Name: context-llemur
Version: 0.2.2
Summary: context-llemur: collaborative memory for humans and LLMs
Author: jerpint
License: MIT
Requires-Python: >=3.11
License-File: LICENSE
Requires-Dist: click>=8.0.0
Requires-Dist: fastmcp>=2.10.2
Requires-Dist: gitpython>=3.1.0
Requires-Dist: tomli_w>=1.0.0
Dynamic: license-file
